rss_toasts/__init__.py
rss_toasts/bg.py
rss_toasts/db.py
rss_toasts/feed.py
rss_toasts/gui.py
rss_toasts/icon.ico
rss_toasts/main.py
rss_toasts-0.2.1.dist-info/LICENSE
rss_toasts-0.2.1.dist-info/METADATA
rss_toasts-0.2.1.dist-info/WHEEL
rss_toasts-0.2.1.dist-info/entry_points.txt
rss_toasts-0.2.1.dist-info/RECORD
